config/__init__.py
config/database.py
models/__init__.py
models/aroma_block.py
models/aroma_track.py
models/base.py
models/cartridge.py
schemas/__init__.py
schemas/aroma_block.py
schemas/aroma_track.py
schemas/cartridge.py
schemas/channel_control_config.py
schemas/interpolation.py
services/__init__.py
services/database_service.py
services/database_service_async.py
tools/db_cli.py
utils/console_printer.py
sensory_db-0.1.0.dist-info/METADATA
sensory_db-0.1.0.dist-info/WHEEL
sensory_db-0.1.0.dist-info/entry_points.txt
sensory_db-0.1.0.dist-info/top_level.txt
sensory_db-0.1.0.dist-info/RECORD
