Metadata-Version: 2.4
Name: sensory_db
Version: 0.1.0
Summary: Sync & async ORM-клиент, сервис-слой и CLI для управления Aroma-данными.
Author-email: SL <info@sensorylab.ru>
License: MIT
Project-URL: Homepage, https://github.com/sensoryfox/sensory_db
Project-URL: Documentation, https://github.com/sensoryfox/sensory_db#readme
Project-URL: Issues, https://github.com/sensoryfox/sensory_db/issues
Project-URL: Changelog, https://github.com/sensoryfox/sensory_db/blob/main/CHANGELOG.md
Keywords: SQLAlchemy,asyncpg,ORM,database,aroma,pydantic,rich,typer
Requires-Python: >=3.9
Requires-Dist: SQLAlchemy<3.0,>=2.0
Requires-Dist: asyncpg>=0.29
Requires-Dist: psycopg2-binary>=2.9
Requires-Dist: pydantic>=2.5
Requires-Dist: rich>=13.0
Requires-Dist: typer[all]>=0.9
Requires-Dist: python-dotenv>=1.0
Provides-Extra: dev
Requires-Dist: pytest>=7.4; extra == "dev"
Requires-Dist: black>=23.10; extra == "dev"
Requires-Dist: isort>=5.12; extra == "dev"
Requires-Dist: mypy>=1.6; extra == "dev"
Provides-Extra: docs
Requires-Dist: mkdocs-material>=9.5; extra == "docs"
